pyroxene/__init__.py
pyroxene/companion_generator.py
pyroxene/device_commands.py
pyroxene/device_proxy.py
pyroxene/elfbackend.py
pyroxene/memory_management.py
pyroxene/cshim/pyroxene.c
pyroxene/cshim/pyroxene.h
pyroxene/cshim/swap.h
pyroxene-1.0.data/scripts/pyroxene_generate_cshim
test/__init__.py
test/test_cffi_compatibility.py
test/test_companion_generator.py
test/test_device_proxy.py
test/test_elfbackend.py
test/test_memory_management.py
test/test_pyroxene.py
pyroxene-1.0.dist-info/LICENSE
pyroxene-1.0.dist-info/METADATA
pyroxene-1.0.dist-info/WHEEL
pyroxene-1.0.dist-info/top_level.txt
pyroxene-1.0.dist-info/RECORD
