Metadata-Version: 2.1
Name: pyroxene
Version: 1.0
Summary: Pyroxene is a Python test interface: Execute tests on remote device using minmal shim and ELF debug data
License: MIT
License-File: LICENSE
Requires-Dist: cffi
Requires-Dist: pcpp
Requires-Dist: pycparser
Requires-Dist: pyelftools
Requires-Dist: pygdbmi
Requires-Dist: pyserial
Requires-Dist: setuptools
Provides-Extra: dev
Requires-Dist: flake8 ; extra == 'dev'
Requires-Dist: black ; extra == 'dev'
Provides-Extra: test
Requires-Dist: hypothesis ; extra == 'test'
